pyboot/dataflowx/context/datasource/__init__.py
pyboot/dataflowx/context/datasource/datasource.py
pyboot/dataflowx/context/datasource/pybatisplus.py
pyboot_datasource-1.3.3.dist-info/licenses/LICENSE
pyboot_datasource-1.3.3.dist-info/METADATA
pyboot_datasource-1.3.3.dist-info/WHEEL
pyboot_datasource-1.3.3.dist-info/top_level.txt
pyboot_datasource-1.3.3.dist-info/RECORD
