Metadata-Version: 2.4
Name: pyboot-datasource
Version: 1.3.3
Summary: Pyboot-datasource is an open-source Python-extended PyBoot component that delivers Spring-WebMVC-like functionality—automatic request mappings, interceptors, RESTful controllers and view resolution—while retaining Spring's convention-over-configuration experience for Python developers.
Author-email: joinsunsoft <793875613@qq.com>
Maintainer-email: joinsunsoft <inthirties.liu@hotmail.com>
License-Expression: Apache-2.0
Requires-Python: >=3.12.10
License-File: LICENSE
Requires-Dist: pyboot-commons-pybatis
Requires-Dist: pyboot-dataflow
Provides-Extra: dev
Requires-Dist: pytest>=6.0.0; extra == "dev"
Requires-Dist: pytest-asyncio>=0.15.0; extra == "dev"
Dynamic: license-file
